trains/__init__.py
trains/train.py
trains/train_functions.py
search_trains-1.0.2.dist-info/LICENSE
search_trains-1.0.2.dist-info/METADATA
search_trains-1.0.2.dist-info/WHEEL
search_trains-1.0.2.dist-info/entry_points.txt
search_trains-1.0.2.dist-info/top_level.txt
search_trains-1.0.2.dist-info/RECORD
