Metadata-Version: 2.1
Name: search-trains
Version: 1.0.2
Summary: A Python package to search trains between stations in India.
Home-page: UNKNOWN
Author: Naveen Tummidi
Author-email: naveentummidi0807@gmail.com
License: MIT
Platform: UNKNOWN
Classifier: License :: OSI Approved :: MIT License
Classifier: Programming Language :: Python :: 2
Classifier: Programming Language :: Python :: 2.7
Requires-Dist: requests
Requires-Dist: tabulate
Requires-Dist: bs4
